csv_position_reader/__init__.py
csv_position_reader-0.1.0.dist-info/METADATA
csv_position_reader-0.1.0.dist-info/RECORD
csv_position_reader-0.1.0.dist-info/WHEEL
csv_position_reader-0.1.0.dist-info/top_level.txt
