Metadata-Version: 2.1
Name: csv-position-reader
Version: 0.1.0
Summary: A custom CSV reader implementation with direct file access
Home-page: https://github.com/loisaidasam/csv-position-reader
Author: @LoisaidaSam
Author-email: sam.sandberg@gmail.com
License: MIT
Keywords: csv
Platform: UNKNOWN
